design.sv

module apb_memory (
    input         pclk,
    input         prst,
    input  [7:0]  paddr,
    input         pwrite,
    input  [7:0]  pwdata,
    input         psel,
    input         penable,
    input         load,
    input         fetch,
    output reg [7:0] prdata,
    output reg    pready,
    output reg    pslverr
);

    reg [7:0] mem [0:127];
    integer i;

    always @(posedge pclk or posedge prst) begin
        if (prst) begin
            for (i = 0; i < 128; i = i + 1)
                mem[i] <= 8'h00;
            pready  <= 1'b0;
            pslverr <= 1'b0;
            prdata  <= 8'h00;
        end
        else begin
            if (load) begin
                $readmemh("image_i.hex", mem);
                $display("Memory initialized from image_i.hex");
            end
            if (fetch) begin
                $writememh("image_o.hex", mem);
                $display("Memory dumped to image_o.hex");
            end

            if (!penable)
                pready <= 1'b0;
            else begin
                pready <= 1'b1; 
                if (psel) begin
                    if (paddr < 128) begin
                        pslverr <= 1'b0;
                        if (pwrite) begin
                            mem[paddr] <= pwdata;
                            $display("WRITE: Addr=%0d Data=%0h", paddr, pwdata);
                        end else begin
                            prdata <= mem[paddr];
                            $display("READ : Addr=%0d Data=%0h", paddr, mem[paddr]);
                        end
                    end else begin
                        pslverr <= 1'b1; 
                    end
                end
            end
        end
    end

endmodule

testbench.sv
`timescale 1ns/1ps

module tb_apb_memory;

    reg pclk, prst;
    reg [7:0] paddr;
    reg pwrite, psel, penable;
    reg [7:0] pwdata;
    reg load, fetch;
    wire [7:0] prdata;
    wire pready, pslverr;

    // Instantiate DUT
    apb_memory dut (
        .pclk(pclk), .prst(prst),
        .paddr(paddr), .pwrite(pwrite), .pwdata(pwdata),
        .psel(psel), .penable(penable),
        .load(load), .fetch(fetch),
        .prdata(prdata), .pready(pready), .pslverr(pslverr)
    );

    // Clock generation
    always #5 pclk = ~pclk;

    initial begin
        // For waveform viewing
        $dumpfile("apb_memory.vcd");
        $dumpvars(0, tb_apb_memory);

        pclk = 0;
        prst = 1; load = 0; fetch = 0;
        psel = 0; penable = 0; pwrite = 0;
        paddr = 0; pwdata = 0;

        #10 prst = 0;

        // Load memory from hex
        load = 1;
        #10 load = 0;

        // Write example
        psel = 1; penable = 1; pwrite = 1;
        paddr = 8'd5; pwdata = 8'hA5;
        #10;

        // Read example
        pwrite = 0;
        paddr = 8'd5;
        #10;

        // Dump memory
        fetch = 1;
        #10 fetch = 0;

        #50 $finish;
    end

endmodule

apb_memory.vcd
$date
	Mon Oct 27 09:29:49 2025
$end
$version
	Icarus Verilog
$end
$timescale
	1ps
$end
$scope module tb_apb_memory $end
$var wire 1 ! pslverr $end
$var wire 1 " pready $end
$var wire 8 # prdata [7:0] $end
$var reg 1 $ fetch $end
$var reg 1 % load $end
$var reg 8 & paddr [7:0] $end
$var reg 1 ' pclk $end
$var reg 1 ( penable $end
$var reg 1 ) prst $end
$var reg 1 * psel $end
$var reg 8 + pwdata [7:0] $end
$var reg 1 , pwrite $end
$scope module dut $end
$var wire 1 $ fetch $end
$var wire 1 % load $end
$var wire 8 - paddr [7:0] $end
$var wire 1 ' pclk $end
$var wire 1 ( penable $end
$var wire 1 ) prst $end
$var wire 1 * psel $end
$var wire 8 . pwdata [7:0] $end
$var wire 1 , pwrite $end
$var reg 8 / prdata [7:0] $end
$var reg 1 " pready $end
$var reg 1 ! pslverr $end
$var integer 32 0 i [31:0] $end
$upscope $end
$upscope $end
$enddefinitions $end
$comment Show the parameter values. $end
$dumpall
$end
#0
$dumpvars
b10000000 0
b0 /
b0 .
b0 -
0,
b0 +
0*
1)
0(
0'
b0 &
0%
0$
b0 #
0"
0!
$end
#5000
b10000000 0
1'
#10000
0'
1%
0)
#15000
1'
#20000
0'
b10100101 +
b10100101 .
b101 &
b101 -
1,
1(
1*
0%
#25000
1"
1'
#30000
0'
0,
#35000
b10100101 #
b10100101 /
1'
#40000
0'
1$
#45000
1'
#50000
0'
0$
